rsaitehu/geometry.py
rsaitehu_geometry-0.0.1.dist-info/METADATA
rsaitehu_geometry-0.0.1.dist-info/WHEEL
rsaitehu_geometry-0.0.1.dist-info/top_level.txt
rsaitehu_geometry-0.0.1.dist-info/RECORD
